yepcord/__init__.py
yepcord/asgi.py
yepcord/cdn/__init__.py
yepcord/cdn/main.py
yepcord/cdn/models.py
yepcord/cli.py
yepcord/gateway/__init__.py
yepcord/gateway/events.py
yepcord/gateway/gateway.py
yepcord/gateway/main.py
yepcord/gateway/presences.py
yepcord/gateway/utils.py
yepcord/remote_auth/__init__.py
yepcord/remote_auth/gateway.py
yepcord/remote_auth/main.py
yepcord/rest_api/__init__.py
yepcord/rest_api/main.py
yepcord/rest_api/models/__init__.py
yepcord/rest_api/models/applications.py
yepcord/rest_api/models/auth.py
yepcord/rest_api/models/channels.py
yepcord/rest_api/models/guilds.py
yepcord/rest_api/models/hypesquad.py
yepcord/rest_api/models/interactions.py
yepcord/rest_api/models/invites.py
yepcord/rest_api/models/oauth2.py
yepcord/rest_api/models/users.py
yepcord/rest_api/models/users_me.py
yepcord/rest_api/models/webhooks.py
yepcord/rest_api/routes/__init__.py
yepcord/rest_api/routes/applications.py
yepcord/rest_api/routes/auth.py
yepcord/rest_api/routes/channels.py
yepcord/rest_api/routes/gifs.py
yepcord/rest_api/routes/guilds.py
yepcord/rest_api/routes/hypesquad.py
yepcord/rest_api/routes/interactions.py
yepcord/rest_api/routes/invites.py
yepcord/rest_api/routes/oauth2.py
yepcord/rest_api/routes/other.py
yepcord/rest_api/routes/teams.py
yepcord/rest_api/routes/users.py
yepcord/rest_api/routes/users_me.py
yepcord/rest_api/routes/webhooks.py
yepcord/rest_api/utils.py
yepcord/yepcord/__init__.py
yepcord/yepcord/classes/__init__.py
yepcord/yepcord/classes/captcha.py
yepcord/yepcord/classes/gifs.py
yepcord/yepcord/classes/other.py
yepcord/yepcord/classes/singleton.py
yepcord/yepcord/config.py
yepcord/yepcord/core.py
yepcord/yepcord/ctx.py
yepcord/yepcord/enums.py
yepcord/yepcord/errors.py
yepcord/yepcord/gateway_dispatcher.py
yepcord/yepcord/models/__init__.py
yepcord/yepcord/models/_utils.py
yepcord/yepcord/models/application.py
yepcord/yepcord/models/application_command.py
yepcord/yepcord/models/attachment.py
yepcord/yepcord/models/audit_log_entry.py
yepcord_server-1.0.0b3.dist-info/LICENSE
yepcord_server-1.0.0b3.dist-info/METADATA
yepcord_server-1.0.0b3.dist-info/WHEEL
yepcord_server-1.0.0b3.dist-info/entry_points.txt
yepcord_server-1.0.0b3.dist-info/RECORD
